pyinaturalist_convert/__init__.py
pyinaturalist_convert/_models.py
pyinaturalist_convert/constants.py
pyinaturalist_convert/converters.py
pyinaturalist_convert/csv.py
pyinaturalist_convert/db.py
pyinaturalist_convert/download.py
pyinaturalist_convert/dwc.py
pyinaturalist_convert/dwca.py
pyinaturalist_convert/fts.py
pyinaturalist_convert/geojson.py
pyinaturalist_convert/gpx.py
pyinaturalist_convert/odp.py
pyinaturalist_convert/py.typed
pyinaturalist_convert/sqlite.py
pyinaturalist_convert/taxonomy.py
pyinaturalist_convert/README.md
pyinaturalist_convert-0.7.2.dist-info/METADATA
pyinaturalist_convert-0.7.2.dist-info/WHEEL
pyinaturalist_convert-0.7.2.dist-info/licenses/LICENSE
pyinaturalist_convert-0.7.2.dist-info/RECORD
