Metadata-Version: 2.4
Name: pyinaturalist-convert
Version: 0.7.2
Summary: Data conversion tools for iNaturalist observations and taxonomy
Project-URL: homepage, https://github.com/pyinat/pyinaturalist-convert
Project-URL: repository, https://github.com/pyinat/pyinaturalist-convert
Project-URL: documentation, https://pyinaturalist-convert.readthedocs.io
Author: Jordan Cook
License-File: LICENSE
Keywords: biodiversity,convert,csv,darwin-core,dataframe,export,gpx,inaturalist
Classifier: Development Status :: 4 - Beta
Classifier: Intended Audience :: Developers
Classifier: Intended Audience :: Education
Classifier: Intended Audience :: Science/Research
Classifier: Typing :: Typed
Requires-Python: >=3.10
Requires-Dist: flatten-dict>=0.4
Requires-Dist: pyinaturalist>=0.20
Requires-Dist: tablib>=3.0
Provides-Extra: db
Requires-Dist: sqlalchemy>=2.0; extra == 'db'
Provides-Extra: dwc
Requires-Dist: xmltodict>=0.12; extra == 'dwc'
Provides-Extra: feather
Requires-Dist: pandas>=1.2; extra == 'feather'
Requires-Dist: pyarrow>=10.0; extra == 'feather'
Provides-Extra: geojson
Requires-Dist: geojson>=2.5; extra == 'geojson'
Provides-Extra: gpx
Requires-Dist: gpxpy>=1.4; extra == 'gpx'
Provides-Extra: hdf
Requires-Dist: pandas>=1.2; extra == 'hdf'
Requires-Dist: tables>=3.6; extra == 'hdf'
Provides-Extra: html
Requires-Dist: jinja2>=3.0; extra == 'html'
Requires-Dist: markuppy>=1.12; extra == 'html'
Provides-Extra: odp
Requires-Dist: boto3>=1.20; extra == 'odp'
Provides-Extra: parquet
Requires-Dist: pandas>=1.2; extra == 'parquet'
Requires-Dist: pyarrow>=10.0; extra == 'parquet'
Provides-Extra: xlsx
Requires-Dist: openpyxl>=2.6; extra == 'xlsx'
Requires-Dist: pandas>=1.2; extra == 'xlsx'
